dotty_dict/__init__.py
dotty_dict/dotty_dict.py
dotty_dict-0.1.9.dist-info/DESCRIPTION.rst
dotty_dict-0.1.9.dist-info/METADATA
dotty_dict-0.1.9.dist-info/RECORD
dotty_dict-0.1.9.dist-info/WHEEL
dotty_dict-0.1.9.dist-info/metadata.json
dotty_dict-0.1.9.dist-info/top_level.txt
