Metadata-Version: 2.0
Name: dotty-dict
Version: 0.1.9
Summary: Dotty dict-like object allow to access deeply nested keys using dot notation.
Home-page: https://github.com/pawelzny/dotty_dict
Author: Paweł Zadrożny
Author-email: pawel.zny@gmail.com
License: MIT license
Keywords: dotty_dict
Platform: UNKNOWN
Classifier: Development Status :: 4 - Beta
Classifier: Intended Audience :: Developers
Classifier: Topic :: Software Development :: Build Tools
Classifier: License :: OSI Approved :: MIT License
Classifier: Programming Language :: Python :: 3.5
Classifier: Programming Language :: Python :: 3.6
